2º carrera/EC/Verilog/Entregable_1/mux2_4.v
//  Multiplexor de 2 entradas a una salida en el que las entradas son de 4 bits. 

module mux2_4(output wire [3:0] Out, input wire [3:0] A, input wire [3:0] B, input wire s);
  
  assign Out = s ? B : A;

endmodule

2º carrera/EC/Verilog/Entregable_1/ENTREGABLE_1/mux4_1.v
// Multiplexor 4 a 1 de 1 bit realizado a partir de puertas

module mux4_1(output reg out, input wire a, b, c, d, input wire [1:0] S);

  always @(*)
  begin
  case(S)
    2'b00: out = a;
    2'b01: out = b;
    2'b10: out = c;
    2'b11: out = d;
  endcase
  end

endmodule

2º carrera/EC/Verilog/Entregable_1/cl.v
// Celda logica

module cl(output wire out, input wire a, b, input wire [1:0] S);

  // Declaramos las conexiones internas
  wire out_and, out_or, out_xor, out_not;

  // Instanciamos las puertas
  and and1 (out_and, a, b);
  or or1 (out_or, a, b);
  xor xor1 (out_xor, a, b);
  not not1 (out_not, a);

  // Instanciamos en el mux 4 a 1
  mux4_1 mux1 (out, out_and, out_or, out_xor, out_not, S);

endmodule

/*
  MODIFICAION: hacerlo de forma behavioral
  assign out = S[1] ? (S[0] ? (a & b) : (a | b)) : (S[0] ? (a ^ b) : (~a));
*/

2º carrera/EC/Verilog/Entregable_1/ul4.v
// Unidad logica de 4 bits de forma estructural usando la cl.v

module ul4(output wire[3:0] Out, input wire[3:0] A, input wire[3:0] B, input wire [1:0] S);

  /* 
    Instanciamos cuatro celdas lógicas para cada bit
    cl cl0 (Out[0], A[0], B[0], S);
    cl cl1 (Out[1], A[1], B[1], S);
    cl cl2 (Out[2], A[2], B[2], S);
    cl cl3 (Out[3], A[3], B[3], S);
  */

  genvar i;
  generate
    for (i = 0; i < 4; i = i + 1) begin
      cl cl_inst (Out[i], A[i], B[i], S); // Instancia de la celda lógica
    end
  endgenerate
  
  /* 
    MODIFICACION: Hacerlo de forma behavioral
    assign Out[3:0] = S[1] ? (S[0] ? (A[3:0] & B[3:0]) : (A[3:0] | B[3:0])) : (S[0] ? (A[3:0] ^ B[3:0]) : (~A[3:0]));
  */
endmodule

2º carrera/EC/Verilog/Entregable_1/sum4_v2.v
//Sumador de 4 bits que no use fa_v1 de 1 bit, sino una asignacion continua y operador concatenacion
module sum4_v2(output wire[3:0] S, output wire c_out, input wire[3:0] A, input wire[3:0] B, input wire c_in);
	
  // Asignamos las salidas
  assign S = A + B + c_in;
  assign c_out = (c_in & A) | (c_in & B) | (A & B);

endmodule

2º carrera/EC/Verilog/Entregable_1/ENTREGABLE_1/compl1.v
// Complementar o no a voluntad, de forma que podamos dejar pasar un dato sin modificar o hacer su complemento a uno

module compl1(output wire [3:0] Out, input wire [3:0] Inp, input wire cpl);

  assign Out = cpl ? ~Inp : Inp;

endmodule

2º carrera/EC/Verilog/Entregable_1/ENTREGABLE_1/alu.v
// Implementación de la ALU en Verilog

module alu(output wire [3:0] R, output wire zero, c_out, sign, input wire [3:0] A, B, 
          input wire c_in, input wire [1:0] ALUOP, input wire l);

 // Declaramos las conexiones internas
  wire [3:0] OP1, OP2;
  wire [3:0] out_mux_1, out_mux_2;
  wire [3:0] out_sum4_1, out_ul4_1;

  // Asignación de las entradas de los multiplexores y el complemento
  wire cpl, add1, op1_A, op2_B;

  assign add1 = ALUOP[0];
  assign op1_A = ((l) | (ALUOP[1] & ~ALUOP[0]));
  assign op2_B = ((l) | (ALUOP[1] & ~ALUOP[0]));
  assign cpl = (~l & ~ALUOP[1] & ALUOP[0]);

  // Declaramos los módulos que vamos a utilizar
  mux2_4 mux1 (out_mux_1, A, B, op2_B);
  compl1 compl (OP2, out_mux_1, cpl);

  mux2_4 mux2 (out_mux_2, 4'b0000, 4'b0001, add1);
  mux2_4 mux3 (OP1, out_mux_2, A, op1_A);
  
  //sum4 sum (out_sum4_1, c_out, OP1, OP2, c_in);
  sum4_v2 sum (out_sum4_1, c_out, OP1, OP2, c_in);
  ul4 ul (out_ul4_1, OP1, OP2, ALUOP);
  mux2_4 mux4 (R, out_sum4_1, out_ul4_1, l);

  // Asignamos las salidas
  assign zero = ~|R;
  assign sign = ~l ? R[3] : 1'bx;
  

endmodule

/**
 * Compilación y ejecución de la simulación
 * iverilog iverilog -o alu alu_tb.v alu.v mux2_4.v compl1.v sum4.v fa_v1.v ul4.v cl.v mux4_1.v
 * iverilog iverilog -o alu alu_tb.v alu.v mux2_4.v compl1.v sum4_v2.v ul4.v cl.v mux4_1.v
 * vvp alu | grep -E -A10 "ERROR|operaciones" | grep -v OK > error.txt
 * Rediriigimos la salida a un fichero para poder analizarla solo con los errores en caso de que los haya
 * Visualizamos los resultados: gtkwave alu.vcd
*/

2º carrera/EC/Verilog/Entregable_1/ENTREGABLE_1/alu_tb.v
// Testbench para modulo alu
`timescale 1 ns / 10 ps //Directiva que fija la unidad de tiempo de simulación y la precision de la unidad
module alu_tb;
//declaracion de señales
reg [1:0] t_Op;
reg t_l, t_cin;
reg [3:0] t_A, t_B; 
wire [3:0] t_R;
wire t_z, t_c, t_s;
integer errores;

// error de cualquier tipo, de resultado, de linea zero, de signo y carry
reg error, error_R, error_z, error_s, error_c; 

//instancia del modulo a testear
alu mat(t_R, t_z, t_c, t_s, t_A, t_B, t_cin, t_Op, t_l);


initial
begin
	$dumpfile("alu.vcd");
	$dumpvars;

	errores = 0;
	t_l = 1'b0;
	repeat(2)
	begin
		t_Op = 2'b0;
		repeat(4)
		begin
			t_cin = 1'b0;
			repeat(2)
			begin
		    	t_A = 4'b0;
		    	repeat(16) 
		    	begin
					t_B = 4'b0;
					repeat(16) 
			  		begin
						#0.01 check;
						#9.99;
						t_B = t_B + 1;
			  		end
			  		t_A = t_A + 1;
		    	end
				t_cin = t_cin + 1;
			end
			t_Op = t_Op + 1;
		end
		t_l = t_l + 1;
	end
	$display("Encontradas %d operaciones erroneas", errores);
  	//fin simulacion
  	$finish;
end

// Tarea para hacer la comprobación automática de resultados
task check;
reg [4:0] expected_R;
reg expected_z, expected_c, expected_s;

begin
	$write("tiempo=%0d A=%b B=%b c_in=%b L=%b OP=%b R=%b, Z=%b, C=%b, S=%b.", $time, t_A, t_B, t_cin, t_l, t_Op, t_R, t_z, t_c, t_s);

	// Si las operaciones son lógicas
	if (t_l)
	begin
		case (t_Op)
			2'b00: expected_R[3:0] = t_A & t_B;
			2'b01: expected_R[3:0] = t_A | t_B;
			2'b10: expected_R[3:0] = t_A ^ t_B;
			2'b11: expected_R[3:0] = ~t_A;
			default: $display("ERROR. Valor no esperado para t_Op: %b", t_Op);
		endcase
		// Se establece a 0, pero realmente es un "don't care"
		expected_c = 1'b0;
		expected_s = expected_R[3];
		// las operaciones lógicas no pueden tener error de signo o acarreo
		error_s = 0;
	 	error_c = 0;
	end
	else
	begin
		case (t_Op)
			2'b00: expected_R = t_A + t_cin;
			2'b01: expected_R = (t_A ^4'b1111) + 4'b0001 + t_cin;
			2'b10: expected_R = t_A + t_B + t_cin;
			2'b11: expected_R = t_A + 1 + t_cin;
			default: $display("ERROR. Valor no esperado para t_Op: %b", t_Op);
		endcase
		expected_c = expected_R[4];
		expected_s = expected_R[3];
		// generacion señales error específicas operaciones aritmeticas
		error_s = (expected_s !== t_s);
	 	error_c = (expected_c !== t_c);
	end

	expected_z = ~| expected_R[3:0];
	// generacion señales error generales para toda la ALU
	error_R = (expected_R[3:0] !== t_R); 
	error_z = (expected_z !== t_z);
	error = error_R | error_z | error_s | error_c;
	if (error)
	begin
		errores = errores + 1;
		$display(" ---- ERROR");
		if (error_R)
			$display("\tResultado esperado %b, obtenido %b", expected_R[3:0], t_R);
		if (error_z)
			$display("\tFlag de cero esperado %b, obtenido %b", expected_z, t_z);
		if (error_s)
			$display("\tFlag de signo esperado %b, obtenido %b", expected_s, t_s);
		if (error_c)
			$display("\tFlag de acarreo esperado %b, obtenido %b", expected_c, t_c);
	end
	else
		$display(" ---- OK");
end
endtask
endmodule

2º carrera/EC/Verilog/Entregable_1/ENTREGABLE_1/alu.vcd
$date
	Tue Oct 24 15:57:52 2023
$end
$version
	Icarus Verilog
$end
$timescale
	10ps
$end
$scope module alu_tb $end
$var wire 1 ! t_z $end
$var wire 1 " t_s $end
$var wire 1 # t_c $end
$var wire 4 $ t_R [3:0] $end
$var reg 1 % error $end
$var reg 1 & error_R $end
$var reg 1 ' error_c $end
$var reg 1 ( error_s $end
$var reg 1 ) error_z $end
$var reg 4 * t_A [3:0] $end
$var reg 4 + t_B [3:0] $end
$var reg 2 , t_Op [1:0] $end
$var reg 1 - t_cin $end
$var reg 1 . t_l $end
$var integer 32 / errores [31:0] $end
$scope module mat $end
$var wire 4 0 A [3:0] $end
$var wire 2 1 ALUOP [1:0] $end
$var wire 4 2 B [3:0] $end
$var wire 1 - c_in $end
$var wire 1 3 cpl $end
$var wire 1 . l $end
$var wire 1 4 op1_A $end
$var wire 1 5 op2_B $end
$var wire 1 ! zero $end
$var wire 1 " sign $end
$var wire 4 6 out_ul4_1 [3:0] $end
$var wire 4 7 out_sum4_1 [3:0] $end
$var wire 4 8 out_mux_2 [3:0] $end
$var wire 4 9 out_mux_1 [3:0] $end
$var wire 1 # c_out $end
$var wire 1 : add1 $end
$var wire 4 ; R [3:0] $end
$var wire 4 < OP2 [3:0] $end
$var wire 4 = OP1 [3:0] $end
$scope module compl $end
$var wire 1 3 cpl $end
$var wire 4 > Out [3:0] $end
$var wire 4 ? Inp [3:0] $end
$upscope $end
$scope module mux1 $end
$var wire 4 @ A [3:0] $end
$var wire 4 A B [3:0] $end
$var wire 1 5 s $end
$var wire 4 B Out [3:0] $end
$upscope $end
$scope module mux2 $end
$var wire 4 C A [3:0] $end
$var wire 4 D B [3:0] $end
$var wire 1 : s $end
$var wire 4 E Out [3:0] $end
$upscope $end
$scope module mux3 $end
$var wire 4 F A [3:0] $end
$var wire 4 G B [3:0] $end
$var wire 1 4 s $end
$var wire 4 H Out [3:0] $end
$upscope $end
$scope module mux4 $end
$var wire 1 . s $end
$var wire 4 I Out [3:0] $end
$var wire 4 J B [3:0] $end
$var wire 4 K A [3:0] $end
$upscope $end
$scope module sum $end
$var wire 4 L A [3:0] $end
$var wire 4 M B [3:0] $end
$var wire 1 - c_in $end
$var wire 1 # c_out $end
$var wire 4 N S [3:0] $end
$upscope $end
$scope module ul $end
$var wire 4 O A [3:0] $end
$var wire 4 P B [3:0] $end
$var wire 2 Q S [1:0] $end
$var wire 4 R Out [3:0] $end
$scope begin genblk1[0] $end
$scope module cl_inst $end
$var wire 2 S S [1:0] $end
$var wire 1 T a $end
$var wire 1 U b $end
$var wire 1 V out_and $end
$var wire 1 W out_not $end
$var wire 1 X out_or $end
$var wire 1 Y out_xor $end
$var wire 1 Z out $end
$scope module mux1 $end
$var wire 2 [ S [1:0] $end
$var wire 1 V a $end
$var wire 1 X b $end
$var wire 1 Y c $end
$var wire 1 W d $end
$var reg 1 Z out $end
$upscope $end
$upscope $end
$upscope $end
$scope begin genblk1[1] $end
$scope module cl_inst $end
$var wire 2 \ S [1:0] $end
$var wire 1 ] a $end
$var wire 1 ^ b $end
$var wire 1 _ out_and $end
$var wire 1 ` out_not $end
$var wire 1 a out_or $end
$var wire 1 b out_xor $end
$var wire 1 c out $end
$scope module mux1 $end
$var wire 2 d S [1:0] $end
$var wire 1 _ a $end
$var wire 1 a b $end
$var wire 1 b c $end
$var wire 1 ` d $end
$var reg 1 c out $end
$upscope $end
$upscope $end
$upscope $end
$scope begin genblk1[2] $end
$scope module cl_inst $end
$var wire 2 e S [1:0] $end
$var wire 1 f a $end
$var wire 1 g b $end
$var wire 1 h out_and $end
$var wire 1 i out_not $end
$var wire 1 j out_or $end
$var wire 1 k out_xor $end
$var wire 1 l out $end
$scope module mux1 $end
$var wire 2 m S [1:0] $end
$var wire 1 h a $end
$var wire 1 j b $end
$var wire 1 k c $end
$var wire 1 i d $end
$var reg 1 l out $end
$upscope $end
$upscope $end
$upscope $end
$scope begin genblk1[3] $end
$scope module cl_inst $end
$var wire 2 n S [1:0] $end
$var wire 1 o a $end
$var wire 1 p b $end
$var wire 1 q out_and $end
$var wire 1 r out_not $end
$var wire 1 s out_or $end
$var wire 1 t out_xor $end
$var wire 1 u out $end
$scope module mux1 $end
$var wire 2 v S [1:0] $end
$var wire 1 q a $end
$var wire 1 s b $end
$var wire 1 t c $end
$var wire 1 r d $end
$var reg 1 u out $end
$upscope $end
$upscope $end
$upscope $end
$upscope $end
$upscope $end
$scope task check $end
$var reg 5 w expected_R [4:0] $end
$var reg 1 x expected_c $end
$var reg 1 y expected_s $end
$var reg 1 z expected_z $end
$upscope $end
$upscope $end
$enddefinitions $end
#0
$dumpvars
xz
xy
xx
bx w
b0 v
0u
0t
0s
1r
0q
0p
0o
b0 n
b0 m
0l
0k
0j
1i
0h
0g
0f
b0 e
b0 d
0c
0b
0a
1`
0_
0^
0]
b0 \
b0 [
0Z
0Y
0X
1W
0V
0U
0T
b0 S
b0 R
b0 Q
b0 P
b0 O
b0 N
b0 M
b0 L
b0 K
b0 J
b0 I
b0 H
b0 G
b0 F
b0 E
b1 D
b0 C
b0 B
b0 A
b0 @
b0 ?
b0 >
b0 =
b0 <
b0 ;
0:
b0 9
b0 8
b0 7
b0 6
05
04
03
b0 2
b0 1
b0 0
b0 /
0.
0-
b0 ,
b0 +
b0 *
x)
x(
x'
x&
x%
b0 $
0#
0"
1!
$end
#1
0%
0)
0&
1z
0'
0(
0y
0x
b0 w
#1000
b1 +
b1 2
b1 A
#2000
b10 +
b10 2
b10 A
#3000
b11 +
b11 2
b11 A
#4000
b100 +
b100 2
b100 A
#5000
b101 +
b101 2
b101 A
#6000
b110 +
b110 2
b110 A
#7000
b111 +
b111 2
b111 A
#8000
b1000 +
b1000 2
b1000 A
#9000
b1001 +
b1001 2
b1001 A
#10000
b1010 +
b1010 2
b1010 A
#11000
b1011 +
b1011 2
b1011 A
#12000
b1100 +
b1100 2
b1100 A
#13000
b1101 +
b1101 2
b1101 A
#14000
b1110 +
b1110 2
b1110 A
#15000
b1111 +
b1111 2
b1111 A
#16000
0!
b1 $
b1 ;
b1 I
1X
1Y
b1 7
b1 K
b1 N
1U
b1 <
b1 >
b1 M
b1 P
b1 9
b1 ?
b1 B
b1 *
b1 0
b1 @
b1 G
b0 +
b0 2
b0 A
#16001
0z
b1 w
#17000
b1 +
b1 2
b1 A
#18000
b10 +
b10 2
b10 A
#19000
b11 +
b11 2
b11 A
#20000
b100 +
b100 2
b100 A
#21000
b101 +
b101 2
b101 A
#22000
b110 +
b110 2
b110 A
#23000
b111 +
b111 2
b111 A
#24000
b1000 +
b1000 2
b1000 A
#25000
b1001 +
b1001 2
b1001 A
#26000
b1010 +
b1010 2
b1010 A
#27000
b1011 +
b1011 2
b1011 A
#28000
b1100 +
b1100 2
b1100 A
#29000
b1101 +
b1101 2
b1101 A
#30000
b1110 +
b1110 2
b1110 A
#31000
b1111 +
b1111 2
b1111 A
#32000
b10 $
b10 ;
b10 I
0X
0Y
1a
1b
b10 7
b10 K
b10 N
0U
1^
b10 <
b10 >
b10 M
b10 P
b10 9
b10 ?
b10 B
b10 *
b10 0
b10 @
b10 G
b0 +
b0 2
b0 A
#32001
b10 w
#33000
b1 +
b1 2
b1 A
#34000
b10 +
b10 2
b10 A
#35000
b11 +
b11 2
b11 A
#36000
b100 +
b100 2
b100 A
#37000
b101 +
b101 2
b101 A
#38000
b110 +
b110 2
b110 A
#39000
b111 +
b111 2
b111 A
#40000
b1000 +
b1000 2
b1000 A
#41000
b1001 +
b1001 2
b1001 A
#42000
b1010 +
b1010 2
b1010 A
#43000
b1011 +
b1011 2
b1011 A
#44000
b1100 +
b1100 2
b1100 A
#45000
b1101 +
b1101 2
b1101 A
#46000
b1110 +
b1110 2
b1110 A
#47000
b1111 +
b1111 2
b1111 A
#48000
b11 $
b11 ;
b11 I
1X
1Y
b11 7
b11 K
b11 N
1U
b11 <
b11 >
b11 M
b11 P
b11 9
b11 ?
b11 B
b11 *
b11 0
b11 @
b11 G
b0 +
b0 2
b0 A
#48001
b11 w
#49000
b1 +
b1 2
b1 A
#50000
b10 +
b10 2
b10 A
#51000
b11 +
b11 2
b11 A
#52000
b100 +
b100 2
b100 A
#53000
b101 +
b101 2
b101 A
#54000
b110 +
b110 2
b110 A
#55000
b111 +
b111 2
b111 A
#56000
b1000 +
b1000 2
b1000 A
#57000
b1001 +
b1001 2
b1001 A
#58000
b1010 +
b1010 2
b1010 A
#59000
b1011 +
b1011 2
b1011 A
#60000
b1100 +
b1100 2
b1100 A
#61000
b1101 +
b1101 2
b1101 A
#62000
b1110 +
b1110 2
b1110 A
#63000
b1111 +
b1111 2
b1111 A
#64000
b100 $
b100 ;
b100 I
0X
0Y
0a
0b
1j
1k
b100 7
b100 K
b100 N
0U
0^
1g
b100 <
b100 >
b100 M
b100 P
b100 9
b100 ?
b100 B
b100 *
b100 0
b100 @
b100 G
b0 +
b0 2
b0 A
#64001
b100 w
#65000
b1 +
b1 2
b1 A
#66000
b10 +
b10 2
b10 A
#67000
b11 +
b11 2
b11 A
#68000
b100 +
b100 2
b100 A
#69000
b101 +
b101 2
b101 A
#70000
b110 +
b110 2
b110 A
#71000
b111 +
b111 2
b111 A
#72000
b1000 +
b1000 2
b1000 A
#73000
b1001 +
b1001 2
b1001 A
#74000
b1010 +
b1010 2
b1010 A
#75000
b1011 +
b1011 2
b1011 A
#76000
b1100 +
b1100 2
b1100 A
#77000
b1101 +
b1101 2
b1101 A
#78000
b1110 +
b1110 2
b1110 A
#79000
b1111 +
b1111 2
b1111 A
#80000
b101 $
b101 ;
b101 I
1X
1Y
b101 7
b101 K
b101 N
1U
b101 <
b101 >
b101 M
b101 P
b101 9
b101 ?
b101 B
b101 *
b101 0
b101 @
b101 G
b0 +
b0 2
b0 A
#80001
b101 w
#81000
b1 +
b1 2
b1 A
#82000
b10 +
b10 2
b10 A
#83000
b11 +
b11 2
b11 A
#84000
b100 +
b100 2
b100 A
#85000
b101 +
b101 2
b101 A
#86000
b110 +
b110 2
b110 A
#87000
b111 +
b111 2
b111 A
#88000
b1000 +
b1000 2
b1000 A
#89000
b1001 +
b1001 2
b1001 A
#90000
b1010 +
b1010 2
b1010 A
#91000
b1011 +
b1011 2
b1011 A
#92000
b1100 +
b1100 2
b1100 A
#93000
b1101 +
b1101 2
b1101 A
#94000
b1110 +
b1110 2
b1110 A
#95000
b1111 +
b1111 2
b1111 A
#96000
b110 $
b110 ;
b110 I
0X
0Y
1a
1b
b110 7
b110 K
b110 N
0U
1^
b110 <
b110 >
b110 M
b110 P
b110 9
b110 ?
b110 B
b110 *
b110 0
b110 @
b110 G
b0 +
b0 2
b0 A
#96001
b110 w
#97000
b1 +
b1 2
b1 A
#98000
b10 +
b10 2
b10 A
#99000
b11 +
b11 2
b11 A
#100000
b100 +
b100 2
b100 A
#101000
b101 +
b101 2
b101 A
#102000
b110 +
b110 2
b110 A
#103000
b111 +
b111 2
b111 A
#104000
b1000 +
b1000 2
b1000 A
#105000
b1001 +
b1001 2
b1001 A
#106000
b1010 +
b1010 2
b1010 A
#107000
b1011 +
b1011 2
b1011 A
#108000
b1100 +
b1100 2
b1100 A
#109000
b1101 +
b1101 2
b1101 A
#110000
b1110 +
b1110 2
b1110 A
#111000
b1111 +
b1111 2
b1111 A
#112000
b111 $
b111 ;
b111 I
1X
1Y
b111 7
b111 K
b111 N
1U
b111 <
b111 >
b111 M
b111 P
b111 9
b111 ?
b111 B
b111 *
b111 0
b111 @
b111 G
b0 +
b0 2
b0 A
#112001
b111 w
#113000
b1 +
b1 2
b1 A
#114000
b10 +
b10 2
b10 A
#115000
b11 +
b11 2
b11 A
#116000
b100 +
b100 2
b100 A
#117000
b101 +
b101 2
b101 A
#118000
b110 +
b110 2
b110 A
#119000
b111 +
b111 2
b111 A
#120000
b1000 +
b1000 2
b1000 A
#121000
b1001 +
b1001 2
b1001 A
#122000
b1010 +
b1010 2
b1010 A
#123000
b1011 +
b1011 2
b1011 A
#124000
b1100 +
b1100 2
b1100 A
#125000
b1101 +
b1101 2
b1101 A
#126000
b1110 +
b1110 2
b1110 A
#127000
b1111 +
b1111 2
b1111 A
#128000
1"
b1000 $
b1000 ;
b1000 I
0X
0Y
0a
0b
0j
0k
1s
1t
b1000 7
b1000 K
b1000 N
0U
0^
0g
1p
b1000 <
b1000 >
b1000 M
b1000 P
b1000 9
b1000 ?
b1000 B
b1000 *
b1000 0
b1000 @
b1000 G
b0 +
b0 2
b0 A
#128001
1y
b1000 w
#129000
b1 +
b1 2
b1 A
#130000
b10 +
b10 2
b10 A
#131000
b11 +
b11 2
b11 A
#132000
b100 +
b100 2
b100 A
#133000
b101 +
b101 2
b101 A
#134000
b110 +
b110 2
b110 A
#135000
b111 +
b111 2
b111 A
#136000
b1000 +
b1000 2
b1000 A
#137000
b1001 +
b1001 2
b1001 A
#138000
b1010 +
b1010 2
b1010 A
#139000
b1011 +
b1011 2
b1011 A
#140000
b1100 +
b1100 2
b1100 A
#141000
b1101 +
b1101 2
b1101 A
#142000
b1110 +
b1110 2
b1110 A
#143000
b1111 +
b1111 2
b1111 A
#144000
b1001 $
b1001 ;
b1001 I
1X
1Y
b1001 7
b1001 K
b1001 N
1U
b1001 <
b1001 >
b1001 M
b1001 P
b1001 9
b1001 ?
b1001 B
b1001 *
b1001 0
b1001 @
b1001 G
b0 +
b0 2
b0 A
#144001
b1001 w
#145000
b1 +
b1 2
b1 A
#146000
b10 +
b10 2
b10 A
#147000
b11 +
b11 2
b11 A
#148000
b100 +
b100 2
b100 A
#149000
b101 +
b101 2
b101 A
#150000
b110 +
b110 2
b110 A
#151000
b111 +
b111 2
b111 A
#152000
b1000 +
b1000 2
b1000 A
#153000
b1001 +
b1001 2
b1001 A
#154000
b1010 +
b1010 2
b1010 A
#155000
b1011 +
b1011 2
b1011 A
#156000
b1100 +
b1100 2
b1100 A
#157000
b1101 +
b1101 2
b1101 A
#158000
b1110 +
b1110 2
b1110 A
#159000
b1111 +
b1111 2
b1111 A
#160000
b1010 $
b1010 ;
b1010 I
0X
0Y
1a
1b
b1010 7
b1010 K
b1010 N
0U
1^
b1010 <
b1010 >
b1010 M
b1010 P
b1010 9
b1010 ?
b1010 B
b1010 *
b1010 0
b1010 @
b1010 G
b0 +
b0 2
b0 A
#160001
b1010 w
#161000
b1 +
b1 2
b1 A
#162000
b10 +
b10 2
b10 A
#163000
b11 +
b11 2
b11 A
#164000
b100 +
b100 2
b100 A
#165000
b101 +
b101 2
b101 A
#166000
b110 +
b110 2
b110 A
#167000
b111 +
b111 2
b111 A
#168000
b1000 +
b1000 2
b1000 A
#169000
b1001 +
b1001 2
b1001 A
#170000
b1010 +
b1010 2
b1010 A
#171000
b1011 +
b1011 2
b1011 A
#172000
b1100 +
b1100 2
b1100 A
#173000
b1101 +
b1101 2
b1101 A
#174000
b1110 +
b1110 2
b1110 A
#175000
b1111 +
b1111 2
b1111 A
#176000
b1011 $
b1011 ;
b1011 I
1X
1Y
b1011 7
b1011 K
b1011 N
1U
b1011 <
b1011 >
b1011 M
b1011 P
b1011 9
b1011 ?
b1011 B
b1011 *
b1011 0
b1011 @
b1011 G
b0 +
b0 2
b0 A
#176001
b1011 w
#177000
b1 +
b1 2
b1 A
#178000
b10 +
b10 2
b10 A
#179000
b11 +
b11 2
b11 A
#180000
b100 +
b100 2
b100 A
#181000
b101 +
b101 2
b101 A
#182000
b110 +
b110 2
b110 A
#183000
b111 +
b111 2
b111 A
#184000
b1000 +
b1000 2
b1000 A
#185000
b1001 +
b1001 2
b1001 A
#186000
b1010 +
b1010 2
b1010 A
#187000
b1011 +
b1011 2
b1011 A
#188000
b1100 +
b1100 2
b1100 A
#189000
b1101 +
b1101 2
b1101 A
#190000
b1110 +
b1110 2
b1110 A
#191000
b1111 +
b1111 2
b1111 A
#192000
b1100 $
b1100 ;
b1100 I
0X
0Y
0a
0b
1j
1k
b1100 7
b1100 K
b1100 N
0U
0^
1g
b1100 <
b1100 >
b1100 M
b1100 P
b1100 9
b1100 ?
b1100 B
b1100 *
b1100 0
b1100 @
b1100 G
b0 +
b0 2
b0 A
#192001
b1100 w
#193000
b1 +
b1 2
b1 A
#194000
b10 +
b10 2
b10 A
#195000
b11 +
b11 2
b11 A
#196000
b100 +
b100 2
b100 A
#197000
b101 +
b101 2
b101 A
#198000
b110 +
b110 2
b110 A
#199000
b111 +
b111 2
b111 A
#200000
b1000 +
b1000 2
b1000 A
#201000
b1001 +
b1001 2
b1001 A
#202000
b1010 +
b1010 2
b1010 A
#203000
b1011 +
b1011 2
b1011 A
#204000
b1100 +
b1100 2
b1100 A
#205000
b1101 +
b1101 2
b1101 A
#206000
b1110 +
b1110 2
b1110 A
#207000
b1111 +
b1111 2
b1111 A
#208000
b1101 $
b1101 ;
b1101 I
1X
1Y
b1101 7
b1101 K
b1101 N
1U
b1101 <
b1101 >
b1101 M
b1101 P
b1101 9
b1101 ?
b1101 B
b1101 *
b1101 0
b1101 @
b1101 G
b0 +
b0 2
b0 A
#208001
b1101 w
#209000
b1 +
b1 2
b1 A
#210000
b10 +
b10 2
b10 A
#211000
b11 +
b11 2
b11 A
#212000
b100 +
b100 2
b100 A
#213000
b101 +
b101 2
b101 A
#214000
b110 +
b110 2
b110 A
#215000
b111 +
b111 2
b111 A
#216000
b1000 +
b1000 2
b1000 A
#217000
b1001 +
b1001 2
b1001 A
#218000
b1010 +
b1010 2
b1010 A
#219000
b1011 +
b1011 2
b1011 A
#220000
b1100 +
b1100 2
b1100 A
#221000
b1101 +
b1101 2
b1101 A
#222000
b1110 +
b1110 2
b1110 A
#223000
b1111 +
b1111 2
b1111 A
#224000
b1110 $
b1110 ;
b1110 I
0X
0Y
1a
1b
b1110 7
b1110 K
b1110 N
0U
1^
b1110 <
b1110 >
b1110 M
b1110 P
b1110 9
b1110 ?
b1110 B
b1110 *
b1110 0
b1110 @
b1110 G
b0 +
b0 2
b0 A
#224001
b1110 w
#225000
b1 +
b1 2
b1 A
#226000
b10 +
b10 2
b10 A
#227000
b11 +
b11 2
b11 A
#228000
b100 +
b100 2
b100 A
#229000
b101 +
b101 2
b101 A
#230000
b110 +
b110 2
b110 A
#231000
b111 +
b111 2
b111 A
#232000
b1000 +
b1000 2
b1000 A
#233000
b1001 +
b1001 2
b1001 A
#234000
b1010 +
b1010 2
b1010 A
#235000
b1011 +
b1011 2
b1011 A
#236000
b1100 +
b1100 2
b1100 A
#237000
b1101 +
b1101 2
b1101 A
#238000
b1110 +
b1110 2
b1110 A
#239000
b1111 +
b1111 2
b1111 A
#240000
b1111 $
b1111 ;
b1111 I
1X
1Y
b1111 7
b1111 K
b1111 N
1U
b1111 <
b1111 >
b1111 M
b1111 P
b1111 9
b1111 ?
b1111 B
b1111 *
b1111 0
b1111 @
b1111 G
b0 +
b0 2
b0 A
#240001
b1111 w
#241000
b1 +
b1 2
b1 A
#242000
b10 +
b10 2
b10 A
#243000
b11 +
b11 2
b11 A
#244000
b100 +
b100 2
b100 A
#245000
b101 +
b101 2
b101 A
#246000
b110 +
b110 2
b110 A
#247000
b111 +
b111 2
b111 A
#248000
b1000 +
b1000 2
b1000 A
#249000
b1001 +
b1001 2
b1001 A
#250000
b1010 +
b1010 2
b1010 A
#251000
b1011 +
b1011 2
b1011 A
#252000
b1100 +
b1100 2
b1100 A
#253000
b1101 +
b1101 2
b1101 A
#254000
b1110 +
b1110 2
b1110 A
#255000
b1111 +
b1111 2
b1111 A
#256000
0"
0X
0Y
0a
0b
0j
0k
0s
0t
0U
0^
0g
0p
0!
b1 $
b1 ;
b1 I
b0 <
b0 >
b0 M
b0 P
b1 7
b1 K
b1 N
0#
b0 9
b0 ?
b0 B
1-
b0 *
b0 0
b0 @
b0 G
b0 +
b0 2
b0 A
#256001
0y
b1 w
#257000
b1 +
b1 2
b1 A
#258000
b10 +
b10 2
b10 A
#259000
b11 +
b11 2
b11 A
#260000
b100 +
b100 2
b100 A
#261000
b101 +
b101 2
b101 A
#262000
b110 +
b110 2
b110 A
#263000
b111 +
b111 2
b111 A
#264000
b1000 +
b1000 2
b1000 A
#265000
b1001 +
b1001 2
b1001 A
#266000
b1010 +
b1010 2
b1010 A
#267000
b1011 +
b1011 2
b1011 A
#268000
b1100 +
b1100 2
b1100 A
#269000
b1101 +
b1101 2
b1101 A
#270000
b1110 +
b1110 2
b1110 A
#271000
b1111 +
b1111 2
b1111 A
#272000
b10 $
b10 ;
b10 I
1X
1Y
b10 7
b10 K
b10 N
1U
b1 <
b1 >
b1 M
b1 P
b1 9
b1 ?
b1 B
b1 *
b1 0
b1 @
b1 G
b0 +
b0 2
b0 A
#272001
b10 w
#273000
b1 +
b1 2
b1 A
#274000
b10 +
b10 2
b10 A
#275000
b11 +
b11 2
b11 A
#276000
b100 +
b100 2
b100 A
#277000
b101 +
b101 2
b101 A
#278000
b110 +
b110 2
b110 A
#279000
b111 +
b111 2
b111 A
#280000
b1000 +
b1000 2
b1000 A
#281000
b1001 +
b1001 2
b1001 A
#282000
b1010 +
b1010 2
b1010 A
#283000
b1011 +
b1011 2
b1011 A
#284000
b1100 +
b1100 2
b1100 A
#285000
b1101 +
b1101 2
b1101 A
#286000
b1110 +
b1110 2
b1110 A
#287000
b1111 +
b1111 2
b1111 A
#288000
b11 $
b11 ;
b11 I
0X
0Y
1a
1b
b11 7
b11 K
b11 N
0U
1^
b10 <
b10 >
b10 M
b10 P
b10 9
b10 ?
b10 B
b10 *
b10 0
b10 @
b10 G
b0 +
b0 2
b0 A
#288001
b11 w
#289000
b1 +
b1 2
b1 A
#290000
b10 +
b10 2
b10 A
#291000
b11 +
b11 2
b11 A
#292000
b100 +
b100 2
b100 A
#293000
b101 +
b101 2
b101 A
#294000
b110 +
b110 2
b110 A
